capture_tag/__init__.py
capture_tag/tests.py
capture_tag/templatetags/__init__.py
capture_tag/templatetags/capture_tags.py
django_capture_tag-1.0.dist-info/DESCRIPTION.rst
django_capture_tag-1.0.dist-info/METADATA
django_capture_tag-1.0.dist-info/RECORD
django_capture_tag-1.0.dist-info/WHEEL
django_capture_tag-1.0.dist-info/metadata.json
django_capture_tag-1.0.dist-info/top_level.txt
